LogExAn/LogicalAnalyser.py
LogExAn/__init__.py
LogExAn/Grammer/SyntaxParser.py
LogExAn/Grammer/__init__.py
LogExAn-1.0.0.dist-info/LICENSE.txt
LogExAn-1.0.0.dist-info/METADATA
LogExAn-1.0.0.dist-info/WHEEL
LogExAn-1.0.0.dist-info/top_level.txt
LogExAn-1.0.0.dist-info/RECORD
